<Properties StartupConfiguration="{BE4932EA-4E03-47A6-8E53-8CB62165EFE4}|Default">
  <MonoDevelop.Ide.DebuggingService.PinnedWatches />
  <MonoDevelop.Ide.Workspace ActiveConfiguration="Debug" />
  <MonoDevelop.Ide.Workbench ActiveDocument="HelloNet/ClientApp/src/components/Home.js">
    <Files>
      <File FileName="HelloNet/ClientApp/src/components/Home.js" Line="155" Column="33" />
      <File FileName="HelloNet/Controllers/AuthController.cs" Line="18" Column="30" />
      <File FileName="HelloNet/appsettings.json" />
      <File FileName="HelloNet/Model/Notes.cs" Line="10" Column="6" />
      <File FileName="HelloNet/DataAccesslayer/AuthDL.cs" Line="192" Column="6" />
      <File FileName="HelloNet/Program.cs" />
      <File FileName="HelloNet/ClientApp/src/AppRoutes.js" />
      <File FileName="HelloNet/DataAccesslayer/IAuthDL.cs" />
      <File FileName="HelloNet/ClientApp/README.md" />
      <File FileName="HelloNet/Model/NotesDbContextFactory.cs" />
      <File FileName="HelloNet/ClientApp/src/components/Notes.css" Line="18" Column="24" />
      <File FileName="HelloNet/ClientApp/src/custom.css" Line="1" Column="1" />
      <File FileName="HelloNet/ClientApp/src/components/layout.css" Line="3" Column="2" />
      <File FileName="HelloNet/ClientApp/src/components/Layout.js" Line="1" Column="1" />
      <File FileName="Tests/UnitTest1.cs" Line="12" Column="1" />
    </Files>
    <Pads>
      <Pad Id="ProjectPad">
        <State name="__root__">
          <Node name="HelloNet" expanded="True">
            <Node name="HelloNet" expanded="True">
              <Node name="Dependencies" expanded="True" />
              <Node name="ClientApp" expanded="True">
                <Node name="src" expanded="True">
                  <Node name="components" expanded="True">
                    <Node name="Home.js" selected="True" />
                  </Node>
                  <Node name="App.js" expanded="True" />
                </Node>
              </Node>
              <Node name="Controllers" expanded="True" />
              <Node name="DataAccesslayer" expanded="True" />
              <Node name="Model" expanded="True" />
              <Node name="Properties" expanded="True" />
            </Node>
            <Node name="Tests" expanded="True" />
          </Node>
        </State>
      </Pad>
    </Pads>
  </MonoDevelop.Ide.Workbench>
  <MonoDevelop.Ide.DebuggingService.Breakpoints>
    <BreakpointStore />
  </MonoDevelop.Ide.DebuggingService.Breakpoints>
  <MultiItemStartupConfigurations />
  <MonoDevelop.Ide.ItemProperties.HelloNet PreferredExecutionTarget="/Applications/Google Chrome.app" />
</Properties>